setup.py
test_components/__init__.py
test_components/zxp_test.py
test_components.egg-info/PKG-INFO
test_components.egg-info/SOURCES.txt
test_components.egg-info/dependency_links.txt
test_components.egg-info/not-zip-safe
test_components.egg-info/top_level.txt
test_components/toolkit/__init__.py
test_components/toolkit/allure_method.py
test_components/toolkit/case_method.py
test_components/toolkit/create_parameters.py
test_components/toolkit/kibana_method.py
test_components/toolkit/log_method.py
test_components/toolkit/mongo_db_method.py
test_components/toolkit/mysql_db_method.py
test_components/toolkit/processing_data.py
test_components/toolkit/tools.py
test_components/toolkit/yaml_method.py